<?xml version="1.0"?>
<PropertyList>

	<path>thrust_flame.ac</path>
	
	<effect>
        <inherits-from>Aircraft/MiG-21bis/Models/Effects/Afterburner/ab-flame</inherits-from>
        <object-name>bounding_box</object-name>
    </effect>
	
    <nopreview/>
    <animation>
        <type>select</type>
        <object-name>bounding_box</object-name>
        <condition>
		<and>
			<property>sim/multiplay/generic/float[8]</property>	
			<not>
				<property>sim/multiplay/generic/float[10]</property>
			</not>
		</and>
        </condition>
    </animation>
	
	
	<animation>
		<type>scale</type>
		<object-name>bounding_box</object-name>
		<property>sim/multiplay/generic/float[9]</property>
		<nopreview/>
		<x-factor>1.0</x-factor>
		<y-factor>0.68</y-factor>
		<z-factor>0.68</z-factor>
	</animation>
	

</PropertyList>
